lcextension/__init__.py
lcextension/ext.py
lcextension/messages.py
lcextension/metrics.py
lcextension/schema.py
lcextension-1.1.10.dist-info/METADATA
lcextension-1.1.10.dist-info/WHEEL
lcextension-1.1.10.dist-info/top_level.txt
lcextension-1.1.10.dist-info/zip-safe
lcextension-1.1.10.dist-info/RECORD
