Metadata-Version: 2.4
Name: lcextension
Version: 1.1.10
Summary: Reference implementation for LimaCharlie.io extensions.
Home-page: https://limacharlie.io
Author: Maxime Lamothe-Brassard ( Refraction Point, Inc )
Author-email: maxime@refractionpoint.com
License: Apache v2
Requires-Dist: limacharlie
Requires-Dist: flask
Dynamic: author
Dynamic: author-email
Dynamic: description
Dynamic: home-page
Dynamic: license
Dynamic: requires-dist
Dynamic: summary
